koalixcrm/__init__.py
koalixcrm/global_support_functions.py
koalixcrm/plugin.py
koalixcrm/version.py
koalixcrm/accounting/__init__.py
koalixcrm/accounting/admin.py
koalixcrm/accounting/exceptions.py
koalixcrm/accounting/models.py
koalixcrm/accounting/views.py
koalixcrm/accounting/accounting/__init__.py
koalixcrm/accounting/accounting/account.py
koalixcrm/accounting/accounting/accounting_period.py
koalixcrm/accounting/accounting/booking.py
koalixcrm/accounting/accounting/product_category.py
koalixcrm/accounting/const/__init__.py
koalixcrm/accounting/const/accountTypeChoices.py
koalixcrm/accounting/factories/__init__.py
koalixcrm/accounting/factories/factory_product_category.py
koalixcrm/accounting/locale/de/LC_MESSAGES/django.mo
koalixcrm/accounting/locale/de/LC_MESSAGES/django.po
koalixcrm/accounting/locale/pt_BR/LC_MESSAGES/django.mo
koalixcrm/accounting/locale/pt_BR/LC_MESSAGES/django.po
koalixcrm/accounting/management/__init__.py
koalixcrm/accounting/management/commands/__init__.py
koalixcrm/accounting/migrations/0001_initial.py
koalixcrm/accounting/migrations/0002_auto_20170705_1702.py
koalixcrm/accounting/migrations/0003_remove_account_originalamount.py
koalixcrm/accounting/migrations/0004_auto_20171009_1949.py
koalixcrm/accounting/migrations/0005_auto_20171110_1732.py
koalixcrm/accounting/migrations/0006_auto_20180422_2048.py
koalixcrm/accounting/migrations/0007_auto_20180422_2105.py
koalixcrm/accounting/migrations/0008_auto_20181012_2056.py
koalixcrm/accounting/migrations/0009_auto_20181012_2056.py
koalixcrm/accounting/migrations/0010_auto_20181216_2224.py
koalixcrm/accounting/migrations/0011_auto_20240329_2207.py
koalixcrm/accounting/migrations/__init__.py
koalixcrm/accounting/rest/__init__.py
koalixcrm/accounting/rest/account_rest.py
koalixcrm/accounting/rest/accounting_period_rest.py
koalixcrm/accounting/rest/booking_rest.py
koalixcrm/accounting/rest/product_categorie_rest.py
koalixcrm/accounting/rest/restinterface.py
koalix_crm-1.14.0.dist-info/LICENSE
koalix_crm-1.14.0.dist-info/METADATA
koalix_crm-1.14.0.dist-info/WHEEL
koalix_crm-1.14.0.dist-info/top_level.txt
koalix_crm-1.14.0.dist-info/RECORD
