Metadata-Version: 2.1
Name: koalix-crm
Version: 1.14.0
Summary: koalixcrm is a tiny and easy to use Customer-Relationship-Management Software (CRM) including tiny and easy to use Accounting Software
Home-page: http://github.com/scaphilo/koalixcrm
Author: Aaron Riedener
Author-email: aaron.riedener@gmail.com
License: BSD
Classifier: Development Status :: 4 - Beta
Classifier: Programming Language :: Python :: 3.10
Requires-Python: ~=3.10
License-File: LICENSE
Requires-Dist: Django ==3.2.25
Requires-Dist: django-filebrowser ==3.14.3
Requires-Dist: lxml ==5.1.0
Requires-Dist: olefile ==0.46
Requires-Dist: Pillow ==10.3.0
Requires-Dist: psycopg2-binary ==2.9.9
Requires-Dist: pytz ==2022.4
Requires-Dist: django-grappelli ==2.15.7
Requires-Dist: djangorestframework ==3.14.0
Requires-Dist: djangorestframework-xml ==2.0.0
Requires-Dist: markdown ==3.1.1
Requires-Dist: django-filter ==23.5
Requires-Dist: pandas ==1.5.3
Requires-Dist: matplotlib ==3.7.5
